rivusio/__init__.py
rivusio/aio/__init__.py
rivusio/aio/parallel.py
rivusio/aio/pipeline.py
rivusio/aio/stream.py
rivusio/cli/__init__.py
rivusio/cli/main.py
rivusio/config/__init__.py
rivusio/config/executor.py
rivusio/config/pipe.py
rivusio/config/stream.py
rivusio/core/__init__.py
rivusio/core/base.py
rivusio/core/exceptions.py
rivusio/core/execution_strategy.py
rivusio/core/message.py
rivusio/core/metrics.py
rivusio/core/types.py
rivusio/monitoring/__init__.py
rivusio/monitoring/metrics.py
rivusio/monitoring/pipeline_monitor.py
rivusio/plugins/__init__.py
rivusio/plugins/plugins.py
rivusio/py.typed
rivusio/sync/__init__.py
rivusio/sync/parallel.py
rivusio/sync/pipeline.py
rivusio/sync/stream.py
rivusio/testing/__init__.py
rivusio/testing/fixtures.py
rivusio-0.2.0.dist-info/LICENSE
rivusio-0.2.0.dist-info/METADATA
rivusio-0.2.0.dist-info/WHEEL
rivusio-0.2.0.dist-info/RECORD
