Metadata-Version: 2.1
Name: rivusio
Version: 0.2.0
Summary: A type-safe, async-first data processing pipeline framework
Home-page: https://github.com/zbytealchemy/rivusio
License: MIT
Keywords: pipeline,data processing,async,sync,type-safe,streaming,etl,data engineering,fast,parallel execution
Author: Zbigniew Mastylo
Author-email: zmastylo@gmail.com
Requires-Python: >=3.10,<4.0
Classifier: License :: OSI Approved :: MIT License
Classifier: Programming Language :: Python :: 3
Classifier: Programming Language :: Python :: 3.10
Classifier: Programming Language :: Python :: 3.11
Requires-Dist: click (>=8.0.0,<9.0.0)
Requires-Dist: pydantic (>=2.5.1,<3.0.0)
Requires-Dist: python-multipart (>=0.0.20,<0.0.21)
Requires-Dist: rich (>=13.7.0,<14.0.0)
Requires-Dist: ruamel.yaml[py-typed] (>=0.18.5,<0.19.0)
Project-URL: Documentation, https://zbytealchemy.github.io/rivusio
Project-URL: Repository, https://github.com/zbytealchemy/rivusio
